pdxpy/__init__.py
pdxpy/converter.py
pdxpy/utils.py
pdxpy-0.1.1.dist-info/LICENSE
pdxpy-0.1.1.dist-info/METADATA
pdxpy-0.1.1.dist-info/WHEEL
pdxpy-0.1.1.dist-info/top_level.txt
pdxpy-0.1.1.dist-info/RECORD
