Metadata-Version: 2.1
Name: pdxpy
Version: 0.1.1
Summary: A small package to convert python data structures to Pdxscript.
Author-email: Rskhm <rskhm.3@gmail.com>
Project-URL: Homepage, https://github.com/xxxAnn/pdxpy
Project-URL: Issues, https://github.com/xxxAnn/pdxpy/issues
Classifier: Programming Language :: Python :: 3
Classifier: License :: OSI Approved :: MIT License
Classifier: Operating System :: OS Independent
Requires-Python: >=3.8
License-File: LICENSE
